doc/Makefile
doc/source/api.rst
doc/source/changelog.rst
doc/source/conf.py
doc/source/index.rst
doc/source/images/GUI_screenshot.png
doc/source/logo/BBP-eModelRunner.jpg
emodelrunner/GUI.py
emodelrunner/__init__.py
emodelrunner/cell.py
emodelrunner/create_cells.py
emodelrunner/create_hoc.py
emodelrunner/create_hoc_tools.py
emodelrunner/create_recordings.py
emodelrunner/create_stimuli.py
emodelrunner/features.py
emodelrunner/json_utilities.py
emodelrunner/load.py
emodelrunner/locations.py
emodelrunner/output.py
emodelrunner/parsing_utilities.py
emodelrunner/recordings.py
emodelrunner/run.py
emodelrunner/run_pairsim.py
emodelrunner/run_synplas.py
emodelrunner/stimuli.py
emodelrunner/synplas_analysis.py
emodelrunner/GUI_utils/__init__.py
emodelrunner/GUI_utils/frames.py
emodelrunner/GUI_utils/interface.py
emodelrunner/GUI_utils/plotshape.py
emodelrunner/GUI_utils/simulator.py
emodelrunner/GUI_utils/style.py
emodelrunner/configuration/__init__.py
emodelrunner/configuration/configparser.py
emodelrunner/configuration/subgroups.py
emodelrunner/configuration/validator.py
emodelrunner/factsheets/__init__.py
emodelrunner/factsheets/experimental_features.py
emodelrunner/factsheets/ion_channel_mechanisms.py
emodelrunner/factsheets/morphology_features.py
emodelrunner/factsheets/output.py
emodelrunner/factsheets/physiology_features.py
emodelrunner/factsheets/units.py
emodelrunner/morphology/__init__.py
emodelrunner/morphology/builder.py
emodelrunner/morphology/morphology.py
emodelrunner/protocols/__init__.py
emodelrunner/protocols/create_protocols.py
emodelrunner/protocols/protocols_func.py
emodelrunner/protocols/reader.py
emodelrunner/protocols/sscx_protocols.py
emodelrunner/protocols/synplas_protocols.py
emodelrunner/protocols/thalamus_protocols.py
emodelrunner/synapses/__init__.py
emodelrunner/synapses/create_locations.py
emodelrunner/synapses/glusynapse.py
emodelrunner/synapses/mechanism.py
emodelrunner/synapses/minis.py
emodelrunner/synapses/recordings.py
EModelRunner-1.2.5.dist-info/AUTHORS.rst
EModelRunner-1.2.5.dist-info/COPYING
EModelRunner-1.2.5.dist-info/LICENSE.txt
EModelRunner-1.2.5.dist-info/METADATA
EModelRunner-1.2.5.dist-info/WHEEL
EModelRunner-1.2.5.dist-info/top_level.txt
EModelRunner-1.2.5.dist-info/RECORD
