Metadata-Version: 2.1
Name: EModelRunner
Version: 1.2.5
Summary: Runs cells from Blue Brain Project cell packages, such as sscx, synapse plasticity, etc.
Author: Blue Brain Project, EPFL
License: EModelRunner is licensed under the Apache License, unless noted otherwise, e.g., for external 
Project-URL: Homepage, https://github.com/BlueBrain/EModelRunner
Project-URL: Source, https://github.com/BlueBrain/EModelRunner
Project-URL: Repository, https://github.com/BlueBrain/EModelRunner.git
Project-URL: Tracker, https://github.com/BlueBrain/EModelRunner/issues
Project-URL: Documentation, https://emodelrunner.readthedocs.io/en/latest
Classifier: Development Status :: 5 - Production/Stable
Classifier: Intended Audience :: Education
Classifier: Intended Audience :: Science/Research
Classifier: Programming Language :: Python
Classifier: Programming Language :: Python :: 3
Classifier: Programming Language :: Python :: 3.8
Classifier: Programming Language :: Python :: 3.9
Classifier: Programming Language :: Python :: 3.10
Classifier: Programming Language :: Python :: 3.11
Classifier: Programming Language :: Python :: 3.12
Classifier: Topic :: Scientific/Engineering :: Bio-Informatics
Requires-Python: >=3.8
License-File: LICENSE.txt
License-File: COPYING
License-File: AUTHORS.rst
Requires-Dist: numpy
Requires-Dist: efel <6,>=4.2
Requires-Dist: bluepyopt >=1.14.15
Requires-Dist: neurom >=3.1.0
Requires-Dist: h5py
Requires-Dist: matplotlib
Requires-Dist: schema
Requires-Dist: Pebble >=4.3.10
Requires-Dist: tqdm >=4.65.0
Provides-Extra: docs
Requires-Dist: sphinx ; extra == 'docs'
Requires-Dist: sphinx-bluebrain-theme ; extra == 'docs'
